aioutils
