Metadata-Version: 1.1
Name: aioutils
Version: 0.3.10
Summary: Python3 Asyncio Utils
Home-page: https://github.com/observerss/aioutils
Author: Jingchao Hu
Author-email: jingchaohu@gmail.com
License: Apache 2.0
Platform: UNKNOWN
Classifier: Development Status :: 5 - Production/Stable
Classifier: Intended Audience :: Developers
Classifier: Natural Language :: English
Classifier: License :: OSI Approved :: Apache Software License
Classifier: Programming Language :: Python :: 3
Classifier: Programming Language :: Python :: 3.4
